lib_uninstaller/__init__.py
lib_uninstaller/installer.py
lib_uninstaller/main.py
lib_uninstaller/upgrader.py
lib_uninstaller-0.1.4.dist-info/licenses/LICENSE.txt
lib_uninstaller-0.1.4.dist-info/METADATA
lib_uninstaller-0.1.4.dist-info/WHEEL
lib_uninstaller-0.1.4.dist-info/entry_points.txt
lib_uninstaller-0.1.4.dist-info/top_level.txt
lib_uninstaller-0.1.4.dist-info/RECORD
