Metadata-Version: 2.4
Name: lib-uninstaller
Version: 0.1.4
Summary: A simple Python package to uninstall selected libraries via CLI
Home-page: https://github.com/yourusername/lib-uninstaller
Author: Your Name
Author-email: your.email@example.com
Classifier: Programming Language :: Python :: 3
Classifier: License :: OSI Approved :: MIT License
Classifier: Operating System :: OS Independent
Requires-Python: >=3.6
License-File: LICENSE.txt
Dynamic: author
Dynamic: author-email
Dynamic: classifier
Dynamic: description
Dynamic: description-content-type
Dynamic: home-page
Dynamic: license-file
Dynamic: requires-python
Dynamic: summary
